psychopy_pyo/__init__.py
psychopy_pyo/backend_pyo.py
psychopy_pyo-0.0.1.dist-info/LICENSE
psychopy_pyo-0.0.1.dist-info/METADATA
psychopy_pyo-0.0.1.dist-info/WHEEL
psychopy_pyo-0.0.1.dist-info/top_level.txt
psychopy_pyo-0.0.1.dist-info/RECORD
