Metadata-Version: 2.1
Name: psychopy-pyo
Version: 0.0.1
Summary: Extension for using Pyo for audio playback.
Author-email: Jon Peirce <jon@opensceincetools.org>, Matthew Cutone <mcutone@opensceincetools.org>
License: GNU General Public License v3 (GPLv3)
Project-URL: homepage, https://github.com/psychopy/psychopy-pyo
Project-URL: changelog, https://github.com/psychopy/psychopy-pyo/blob/main/CHANGELOG.txt
Project-URL: documentation, https://pages.github.com/psychopy/psychopy-pyo
Project-URL: repository, https://github.com/psychopy/psychopy-pyo
Classifier: License :: OSI Approved :: GNU General Public License v3 (GPLv3)
Classifier: Programming Language :: Python :: 3
Classifier: Programming Language :: Python :: 3 :: Only
Classifier: Programming Language :: Python :: 3.7
Classifier: Programming Language :: Python :: 3.8
Classifier: Programming Language :: Python :: 3.9
Classifier: Programming Language :: Python :: 3.10
Classifier: Programming Language :: Python :: 3.11
Classifier: Programming Language :: Python :: Implementation :: CPython
Requires-Python: >=3.7
License-File: LICENSE
